README.md
setup.cfg
setup.py
gsmHat/__init__.py
gsmHat/gsmHat.py
gsmHat.egg-info/PKG-INFO
gsmHat.egg-info/SOURCES.txt
gsmHat.egg-info/dependency_links.txt
gsmHat.egg-info/requires.txt
gsmHat.egg-info/top_level.txt