Metadata-Version: 2.1
Name: gsmHat
Version: 0.4.2
Summary: Using the Waveshare GSM/GPRS/GNSS Hat for Raspberry Pi with Python
Home-page: https://github.com/Civlo85/gsmHat
Author: Tarek Tounsi
Author-email: software@tounsi.de
License: MIT
Download-URL: https://github.com/Civlo85/gsmHat/archive/v_04.tar.gz
Keywords: Waveshare,GSM,GPS,Raspberry,Pi
Platform: UNKNOWN
Classifier: Development Status :: 3 - Alpha
Classifier: Intended Audience :: Developers
Classifier: Topic :: Software Development :: Build Tools
Classifier: License :: OSI Approved :: MIT License
Classifier: Programming Language :: Python :: 3
Classifier: Programming Language :: Python :: 3.4
Classifier: Programming Language :: Python :: 3.5
Classifier: Programming Language :: Python :: 3.6
Classifier: Programming Language :: Python :: 3.7
